statute_utils/__init__.py
statute_utils/__main__.py
statute_utils/extractor.py
statute_utils/fetcher.py
statute_utils/models.py
statute_utils/models_names.py
statute_utils/models_serials.py
statute_utils/templater.py
statute_utils/tree.py
statute_utils/tree_codification.py
statute_utils/tree_statute.py
statute_utils/components/__init__.py
statute_utils/components/branch.py
statute_utils/components/builder.py
statute_utils/components/sections.py
statute_utils/components/short.py
statute_utils/components/utils.py
statute_utils/sql/cite_statute_as_codification.sql
statute_utils/sql/cite_statute_in_codifications.sql
statute_utils/sql/cite_statute_in_statute_units.sql
statute_utils/sql/cite_statute_in_unique_statutes.sql
statute_utils/sql/view_future_statute_units.sql
statute_utils/sql/view_statute_references.sql
statute_utils/sql/view_statutes_affecting_codifications.sql
statute_utils/templates/__init__.py
statute_utils/templates/crumbs.html
statute_utils/templates/paragraph.html
statute_utils/templates/subtree.html
statute_utils/templates/tree.css
statute_utils/templates/tree.html
statute_utils/templates/__pycache__/__init__.cpython-312.pyc
statute_utils/templates/__pycache__/__init__.cpython-313.pyc
statute_utils-0.9.2.dist-info/METADATA
statute_utils-0.9.2.dist-info/WHEEL
statute_utils-0.9.2.dist-info/entry_points.txt
statute_utils-0.9.2.dist-info/top_level.txt
statute_utils-0.9.2.dist-info/RECORD
