Metadata-Version: 2.4
Name: statute-utils
Version: 0.9.2
Summary: Toolkit for Philippine rules.
Requires-Python: >=3.13
Requires-Dist: prelawsql>=0.0.13
Requires-Dist: markdownify>=1.2.0
Requires-Dist: jinja2>=3.1.6
Requires-Dist: lxml>=6.0.0
